[
  {
    "paramName": "issm",
    "paramLongName": "isSparkSessionManaged",
    "paramDescription": "when true will stop SparkSession after job execution",
    "paramRequired": false
  },
  {
    "paramName": "irp",
    "paramLongName": "inputRelatedEntitiesPath",
    "paramDescription": "path to input relations from the graph",
    "paramRequired": true
  },
  {
    "paramName": "iep",
    "paramLongName": "inputGraphPath",
    "paramDescription": "root graph path",
    "paramRequired": true
  },
  {
    "paramName": "op",
    "paramLongName": "outputPath",
    "paramDescription": "root output location for prepared relations",
    "paramRequired": true
  }
]
