[
	{
		"paramName":"pip",
		"paramLongName":"preparedInfoPath",
		"paramDescription": "the path of the prepared resultid of allowed pids file to read",
		"paramRequired": true
	},
	{
		"paramName": "out",
		"paramLongName": "outputPath",
		"paramDescription": "the path used to store the entire set of the prepared info",
		"paramRequired": true
	},
	{
		"paramName": "ssm",
		"paramLongName": "isSparkSessionManaged",
		"paramDescription": "true if the spark session is managed, false otherwise",
		"paramRequired": false
	}
]


